MANIFEST.in
README.rst
setup.py
cloudmanager_micropython_esp8266/__init__.py
cloudmanager_micropython_esp8266.egg-info/PKG-INFO
cloudmanager_micropython_esp8266.egg-info/SOURCES.txt
cloudmanager_micropython_esp8266.egg-info/dependency_links.txt
cloudmanager_micropython_esp8266.egg-info/not-zip-safe
cloudmanager_micropython_esp8266.egg-info/requires.txt
cloudmanager_micropython_esp8266.egg-info/top_level.txt
cloudmanager_micropython_esp8266/firmware/circuitpython-firmware-combined.bin
cloudmanager_micropython_esp8266/firmware/micropython-firmware-combined.bin
cloudmanager_micropython_esp8266/firmware/micropython-v1.8.6-firmware-combined.bin
scripts/configure_esp_image
scripts/esp_terminal
scripts/flash_esp_image