Metadata-Version: 1.2
Name: cloudmanager-micropython-esp8266
Version: 1.9.70
Summary: Cloudmanager esp8266 flash image
Home-page: https://github.com/dwighthubbard/cloudmanager-micropython-esp8266
Author: Dwight Hubbard
Author-email: dwight@dwighthubbard.com
Maintainer: Dwight Hubbard
Maintainer-email: dwight@dwighthubbard.com
License: MIT
Platform: UNKNOWN
